finch/__init__.py
finch/finch.cpython-312-x86_64-linux-gnu.so
finch_sketch-0.6.2.dist-info/METADATA
finch_sketch-0.6.2.dist-info/WHEEL
finch_sketch-0.6.2.dist-info/licenses/LICENSE.txt
finch_sketch-0.6.2.dist-info/RECORD
