Metadata-Version: 2.4
Name: finch-sketch
Version: 0.6.2
License-File: LICENSE.txt
Summary: An implementation of min-wise independent permutation locality sensitive hashing ('MinHashing') for genomic data and command-line utility for manipulation.
Keywords: minhash,bioinformatics,sketches
Author: One Codex <vincent@onecodex.com>
Author-email: One Codex <vincent@onecodex.com>
License: MIT
Project-URL: Source Code, https://github.com/onecodex/finch-rs
